{
  "version": "5",
  "dialect": "sqlite",
  "entries": [
    {
      "idx": 0,
      "version": "5",
      "when": 1707330063104,
      "tag": "0000_pretty_wallop",
      "breakpoints": true
    },
    {
      "idx": 1,
      "version": "5",
      "when": 1707388987762,
      "tag": "0001_silent_shiva",
      "breakpoints": true
    },
    {
      "idx": 2,
      "version": "5",
      "when": 1707395287196,
      "tag": "0002_odd_squirrel_girl",
      "breakpoints": true
    },
    {
      "idx": 3,
      "version": "5",
      "when": 1707523485955,
      "tag": "0003_famous_sersi",
      "breakpoints": true
    }
  ]
}